contentctl/__init__.py
contentctl/actions/build.py
contentctl/actions/deploy_acs.py
contentctl/actions/detection_testing/DetectionTestingManager.py
contentctl/actions/detection_testing/GitService.py
contentctl/actions/detection_testing/generate_detection_coverage_badge.py
contentctl/actions/detection_testing/infrastructures/DetectionTestingInfrastructure.py
contentctl/actions/detection_testing/infrastructures/DetectionTestingInfrastructureContainer.py
contentctl/actions/detection_testing/infrastructures/DetectionTestingInfrastructureServer.py
contentctl/actions/detection_testing/progress_bar.py
contentctl/actions/detection_testing/views/DetectionTestingView.py
contentctl/actions/detection_testing/views/DetectionTestingViewCLI.py
contentctl/actions/detection_testing/views/DetectionTestingViewFile.py
contentctl/actions/detection_testing/views/DetectionTestingViewWeb.py
contentctl/actions/doc_gen.py
contentctl/actions/initialize.py
contentctl/actions/inspect.py
contentctl/actions/new_content.py
contentctl/actions/release_notes.py
contentctl/actions/reporting.py
contentctl/actions/test.py
contentctl/actions/validate.py
contentctl/api.py
contentctl/contentctl.py
contentctl/enrichments/attack_enrichment.py
contentctl/enrichments/cve_enrichment.py
contentctl/enrichments/splunk_app_enrichment.py
contentctl/helper/link_validator.py
contentctl/helper/logger.py
contentctl/helper/splunk_app.py
contentctl/helper/utils.py
contentctl/input/director.py
contentctl/input/new_content_questions.py
contentctl/input/yml_reader.py
contentctl/objects/abstract_security_content_objects/detection_abstract.py
contentctl/objects/abstract_security_content_objects/security_content_object_abstract.py
contentctl/objects/alert_action.py
contentctl/objects/annotated_types.py
contentctl/objects/atomic.py
contentctl/objects/base_security_event.py
contentctl/objects/base_test.py
contentctl/objects/base_test_result.py
contentctl/objects/baseline.py
contentctl/objects/baseline_tags.py
contentctl-5.5.10.dist-info/METADATA
contentctl-5.5.10.dist-info/WHEEL
contentctl-5.5.10.dist-info/entry_points.txt
contentctl-5.5.10.dist-info/licenses/LICENSE.md
contentctl-5.5.10.dist-info/RECORD
