Metadata-Version: 2.4
Name: contentctl
Version: 5.5.10
Summary: Splunk Content Control Tool
License: Apache 2.0
License-File: LICENSE.md
Author: STRT
Author-email: research@splunk.com
Requires-Python: >=3.11,<3.14
Classifier: License :: Other/Proprietary License
Classifier: Programming Language :: Python :: 3
Classifier: Programming Language :: Python :: 3.11
Classifier: Programming Language :: Python :: 3.12
Classifier: Programming Language :: Python :: 3.13
Requires-Dist: Jinja2 (>=3.1.4,<4.0.0)
Requires-Dist: PyYAML (>=6.0.2,<7.0.0)
Requires-Dist: attackcti (>=0.5.4,<0.6)
Requires-Dist: bottle (>=0.12.25,<0.14.0)
Requires-Dist: docker (>=7.1.0,<8.0.0)
Requires-Dist: gitpython (>=3.1.43,<4.0.0)
Requires-Dist: pycvesearch (>=1.2,<2.0)
Requires-Dist: pydantic (>=2.9.2,<2.10.0)
Requires-Dist: pygit2 (>=1.15.1,<2.0.0)
Requires-Dist: questionary (>=2.0.1,<3.0.0)
Requires-Dist: requests (>=2.32.4)
Requires-Dist: rich (>=14.0.0,<15.0.0)
Requires-Dist: semantic-version (>=2.10.0,<3.0.0)
Requires-Dist: setuptools (>=80.9.0)
Requires-Dist: splunk-sdk (>=2.0.2,<3.0.0)
Requires-Dist: tqdm (>=4.66.5,<5.0.0)
Requires-Dist: tyro (>=0.9.2,<0.9.23)
Requires-Dist: xmltodict (>=0.13,<0.15)
